odoo/addons/web_dialog_size/README.rst
odoo/addons/web_dialog_size/__init__.py
odoo/addons/web_dialog_size/__manifest__.py
odoo/addons/web_dialog_size/i18n/de.po
odoo/addons/web_dialog_size/i18n/es.po
odoo/addons/web_dialog_size/i18n/fr.po
odoo/addons/web_dialog_size/i18n/it.po
odoo/addons/web_dialog_size/i18n/nl.po
odoo/addons/web_dialog_size/i18n/web_dialog_size.pot
odoo/addons/web_dialog_size/i18n/zh_CN.po
odoo/addons/web_dialog_size/models/__init__.py
odoo/addons/web_dialog_size/models/ir_config_parameter.py
odoo/addons/web_dialog_size/readme/CONFIGURE.md
odoo/addons/web_dialog_size/readme/CONTRIBUTORS.md
odoo/addons/web_dialog_size/readme/DESCRIPTION.md
odoo/addons/web_dialog_size/readme/ROADMAP.md
odoo/addons/web_dialog_size/static/description/icon.png
odoo/addons/web_dialog_size/static/description/index.html
odoo/addons/web_dialog_size/static/src/js/web_dialog_size.esm.js
odoo/addons/web_dialog_size/static/src/scss/web_dialog_size.scss
odoo/addons/web_dialog_size/static/src/xml/ExpandButton.xml
odoo/addons/web_dialog_size/static/src/xml/select_create_dialog.xml
odoo/addons/web_dialog_size/static/src/xml/web_dialog_header.xml
odoo/addons/web_dialog_size/tests/__init__.py
odoo/addons/web_dialog_size/tests/test_web_dialog_size.py
odoo_addon_web_dialog_size-18.0.1.0.1.dist-info/METADATA
odoo_addon_web_dialog_size-18.0.1.0.1.dist-info/WHEEL
odoo_addon_web_dialog_size-18.0.1.0.1.dist-info/top_level.txt
odoo_addon_web_dialog_size-18.0.1.0.1.dist-info/RECORD
