Metadata-Version: 2.1
Name: odoo-addon-web_dialog_size
Version: 18.0.1.0.1
Requires-Python: >=3.10
Requires-Dist: odoo==18.0.*
Summary: A module that lets the user expand a dialog box to the full screen width.
Home-page: https://github.com/OCA/web
License: AGPL-3
Author: ACSONE SA/NV, Therp BV, Siddharth Bhalgami,Tecnativa, Amaris, Odoo Community Association (OCA)
Author-email: support@odoo-community.org
Classifier: Programming Language :: Python
Classifier: Framework :: Odoo
Classifier: Framework :: Odoo :: 18.0
Classifier: License :: OSI Approved :: GNU Affero General Public License v3
